README.md
setup.cfg
setup.py
rohit/__init__.py
rohit.egg-info/PKG-INFO
rohit.egg-info/SOURCES.txt
rohit.egg-info/dependency_links.txt
rohit.egg-info/top_level.txt