Metadata-Version: 2.1
Name: rohit
Version: 0.0.1
Summary: Rohit Sanjay's Python Package
Home-page: https://github.com/rohitsanj/rohit
Author: Rohit Sanjay
Author-email: sanjay.rohit2@gmail.com
License: UNKNOWN
Platform: UNKNOWN
Classifier: License :: OSI Approved :: MIT License
Classifier: Operating System :: OS Independent
